dashr_tools/__init__.py
dashr_tools/bin_reader.py
dashr_tools/dashr_data.py
dashr_tools-1.3.0.dist-info/METADATA
dashr_tools-1.3.0.dist-info/WHEEL
dashr_tools-1.3.0.dist-info/RECORD
