Metadata-Version: 2.4
Name: dashr-tools
Version: 1.3.0
Summary: Toolkit to interface with Duke Injury Biomechanics Laboratory DASHR device data.
Author: mzabrams
Author-email: mitchell.abrams@duke.edu>
Requires-Python: >=3.12.0,<3.14.0
Classifier: Development Status :: 5 - Production/Stable
Classifier: Programming Language :: Python :: 3
Classifier: Programming Language :: Python :: 3.12
Classifier: Programming Language :: Python :: 3.13
Classifier: Topic :: Scientific/Engineering
Requires-Dist: coverage (>=7.6.10,<8.0.0)
Requires-Dist: matplotlib (>=3.10.1,<4.0.0)
Requires-Dist: myst-parser (>=4.0.1,<5.0.0)
Requires-Dist: natsort (>=8.4.0,<9.0.0)
Requires-Dist: numpy (>=2.2)
Requires-Dist: pandas (>=2.2.0)
Requires-Dist: pydantic (>=2.11.7,<3.0.0)
Requires-Dist: pydata-sphinx-theme (>=0.16.1,<0.17.0)
Requires-Dist: pytest (>=8.3.4,<9.0.0)
Requires-Dist: rinohtype (>=0.5.5,<0.6.0)
Requires-Dist: sphinx (>=8.2.3,<9.0.0)
Requires-Dist: tqdm (>=4.67.1,<5.0.0)
Project-URL: Documentation, https://biomechanics.pages.oit.duke.edu/dashr-tools/html/
Project-URL: Homepage, https://gitlab.oit.duke.edu/biomechanics/dashr-tools
Project-URL: Repository, https://gitlab.oit.duke.edu/biomechanics/dashr-tools
